{
  "reward": {
    "warmup_steps": 0,
    "variables": {
      "triforce": {
        "reward": 300,
        "delta": "signed",
        "max_delta": 1
      },
      "hearts": {
        "penalty": 0.5,
        "max_delta": 1
      },
      "heart_fraction": {
        "penalty": 0.00390625
      }
    },
    "milestones": {
      "got_sword": {
        "var": "sword",
        "op": "greater-than",
        "reference": 0,
        "reward": 50
      },
      "entered_dungeon1": {
        "var": "level",
        "op": "equal",
        "reference": 1,
        "reward": 100
      },
      "died": {
        "var": "game_mode",
        "op": "equal",
        "reference": 17,
        "reward": -10
      }
    },
    "novelty": {
      "screens": {
        "keys": [
          "level",
          "screen_id"
        ],
        "reward": 3.0
      }
    },
    "counters": {
      "screen_kills": {
        "var": "kills",
        "context": [
          "level",
          "screen_id"
        ],
        "reward": 2.0,
        "decay": 0.5,
        "max_per_context": 6,
        "max_event_delta": 3
      },
      "keys_found": {
        "var": "keys",
        "context": [
          "level"
        ],
        "reward": 5.0,
        "decay": 1.0,
        "max_per_context": 6,
        "max_event_delta": 1
      }
    }
  },
  "done": {
    "variables": {
      "game_mode": {
        "op": "equal",
        "reference": 17
      }
    }
  }
}